pypare/__init__.py
pypare/config.py
pypare/logging.py
pypare/plugins.py
pypare/pypi/__init__.py
pypare/pypi/model.py
pypare/pypi/templates/simple.j2
pypare/pypi/templates/simple_package.j2
pypare/scripts/__init__.py
pypare/utils.py
pypare-0.3.3.dist-info/entry_points.txt
pypare-0.3.3.dist-info/LICENSE.txt
pypare-0.3.3.dist-info/WHEEL
pypare-0.3.3.dist-info/METADATA
pypare-0.3.3.dist-info/RECORD
