Metadata-Version: 2.1
Name: pypare
Version: 0.3.3
Summary: A very simple pypi cache
Home-page: https://github.com/diefans/pypare
License: Apache-2.0
Keywords: pypi,cache,asyncio
Author: Oliver Berger
Author-email: oliver@digitalarchitekt.de
Requires-Python: >=3.6,<4.0
Classifier: License :: OSI Approved :: Apache Software License
Classifier: Programming Language :: Python :: 3
Classifier: Programming Language :: Python :: 3.6
Classifier: Programming Language :: Python :: 3.7
Requires-Dist: aiofile (>=1.4,<2.0)
Requires-Dist: aiofiles (>=0.4.0,<0.5.0)
Requires-Dist: aiohttp (>=3.4,<4.0)
Requires-Dist: aiohttp-jinja2 (>=1.1,<2.0)
Requires-Dist: aiotask_context (>=0.6.0,<0.7.0)
Requires-Dist: click (>=7.0,<8.0)
Requires-Dist: colorama (>=0.3.9,<0.4.0)
Requires-Dist: inotipy (>=0.1.1,<0.2.0)
Requires-Dist: packaging (>=18.0,<19.0)
Requires-Dist: structlog (>=18.2,<19.0)
Project-URL: Repository, https://github.com/diefans/pypare
